django_zato/__init__.py
django_zato/client.py
django_zato/ctx.py
django_zato/middleware.py
django_zato/settings.py
django_zato_plugin-4.1.4.dist-info/METADATA
django_zato_plugin-4.1.4.dist-info/WHEEL
django_zato_plugin-4.1.4.dist-info/RECORD
