Metadata-Version: 2.4
Name: django-zato-plugin
Version: 4.1.4
Summary: Django plugin for Zato
Project-URL: Homepage, https://zato.io
Project-URL: Documentation, https://zato.io/docs
Project-URL: Repository, https://github.com/zatosource/zato
Author-email: "Zato Source s.r.o." <info@zato.io>
License-Expression: AGPL-3.0
Classifier: Development Status :: 5 - Production/Stable
Classifier: Environment :: Web Environment
Classifier: Framework :: Django
Classifier: Intended Audience :: Developers
Classifier: License :: OSI Approved :: GNU Affero General Public License v3
Classifier: Operating System :: OS Independent
Classifier: Programming Language :: Python :: 3
Classifier: Programming Language :: Python :: 3.10
Classifier: Programming Language :: Python :: 3.11
Classifier: Programming Language :: Python :: 3.12
Classifier: Topic :: Internet :: WWW/HTTP
Requires-Python: >=3.12
Requires-Dist: requests
